camfr/__init__.py
camfr-0.0.0.dist-info/LICENSE
camfr-0.0.0.dist-info/METADATA
camfr-0.0.0.dist-info/WHEEL
camfr-0.0.0.dist-info/top_level.txt
camfr-0.0.0.dist-info/RECORD
