Metadata-Version: 2.1
Name: camfr
Version: 0.0.0
Summary: Camfr: the Cavity Modeling Framework. 
Home-page: http://github.com/flaport/camfr
Author: Peter Bienstman
Author-email: floris.laporte@gmail.com
License: UNKNOWN
Platform: UNKNOWN
Classifier: Programming Language :: Python :: 3
Classifier: Development Status :: 3 - Alpha
Classifier: Operating System :: OS Independent
Classifier: License :: OSI Approved :: Apache Software License
Classifier: Topic :: Scientific/Engineering
Classifier: Topic :: Scientific/Engineering :: Physics
